LICENSE.txt
setup.cfg
setup.py
sapiens_transformers/__init__.py
sapiens_transformers/activations.py
sapiens_transformers/activations_tf.py
sapiens_transformers/adaptations.py
sapiens_transformers/audio_utils.py
sapiens_transformers/cache_utils.py
sapiens_transformers/configuration_utils.py
sapiens_transformers/convert_graph_to_onnx.py
sapiens_transformers/convert_pytorch_checkpoint_to_tf2.py
sapiens_transformers/convert_slow_tokenizer.py
sapiens_transformers/convert_slow_tokenizers_checkpoints_to_fast.py
sapiens_transformers/convert_tf_hub_seq_to_seq_bert_to_pytorch.py
sapiens_transformers/debug_utils.py
sapiens_transformers/deepspeed.py
sapiens_transformers/dependency_versions_check.py
sapiens_transformers/dependency_versions_table.py
sapiens_transformers/download.py
sapiens_transformers/dynamic_module_utils.py
sapiens_transformers/feature_extraction_sequence_utils.py
sapiens_transformers/feature_extraction_utils.py
sapiens_transformers/file_utils.py
sapiens_transformers/hf_argparser.py
sapiens_transformers/hyperparameter_search.py
sapiens_transformers/image_processing_base.py
sapiens_transformers/image_processing_utils.py
sapiens_transformers/image_processing_utils_fast.py
sapiens_transformers/image_transforms.py
sapiens_transformers/image_utils.py
sapiens_transformers/inference.py
sapiens_transformers/keras_callbacks.py
sapiens_transformers/modelcard.py
sapiens_transformers/modeling_attn_mask_utils.py
sapiens_transformers/modeling_flash_attention_utils.py
sapiens_transformers/modeling_flax_outputs.py
sapiens_transformers/modeling_flax_pytorch_utils.py
sapiens_transformers/modeling_flax_utils.py
sapiens_transformers/modeling_gguf_pytorch_utils.py
sapiens_transformers/modeling_outputs.py
sapiens_transformers/modeling_rope_utils.py
sapiens_transformers/modeling_tf_outputs.py
sapiens_transformers/modeling_tf_pytorch_utils.py
sapiens_transformers/modeling_tf_utils.py
sapiens_transformers/modeling_utils.py
sapiens_transformers/optimization.py
sapiens_transformers.egg-info/PKG-INFO
sapiens_transformers.egg-info/SOURCES.txt
sapiens_transformers.egg-info/dependency_links.txt
sapiens_transformers.egg-info/requires.txt
sapiens_transformers.egg-info/top_level.txt
